aurora_cli/__init__.py
aurora_cli/__main__.py
aurora_cli/src/__init__.py
aurora_cli/src/api/__init__.py
aurora_cli/src/api/group_api.py
aurora_cli/src/api/routes/__init__.py
aurora_cli/src/api/routes/routes_app.py
aurora_cli/src/api/routes/routes_apps.py
aurora_cli/src/api/routes/routes_device.py
aurora_cli/src/api/routes/routes_emulator.py
aurora_cli/src/api/routes/routes_flutter.py
aurora_cli/src/api/routes/routes_psdk.py
aurora_cli/src/api/routes/routes_sdk.py
aurora_cli/src/api/routes/routes_settings.py
aurora_cli/src/api/routes/routes_tests.py
aurora_cli/src/api/routes/routes_vscode.py
aurora_cli/src/base/__init__.py
aurora_cli/src/base/common/__init__.py
aurora_cli/src/base/common/features/__init__.py
aurora_cli/src/base/common/features/flutter_features.py
aurora_cli/src/base/common/features/image_features.py
aurora_cli/src/base/common/features/load_by_version.py
aurora_cli/src/base/common/features/request_version.py
aurora_cli/src/base/common/features/search_files.py
aurora_cli/src/base/common/features/search_installed.py
aurora_cli/src/base/common/features/shell_features.py
aurora_cli/src/base/common/features/shell_pip.py
aurora_cli/src/base/common/features/shell_vscode.py
aurora_cli/src/base/common/features/ssh_features.py
aurora_cli/src/base/common/groups/__init__.py
aurora_cli/src/base/common/groups/app/__init__.py
aurora_cli/src/base/common/groups/app/app_features.py
aurora_cli/src/base/common/groups/apps/__init__.py
aurora_cli/src/base/common/groups/apps/apps_features.py
aurora_cli/src/base/common/groups/common/__init__.py
aurora_cli/src/base/common/groups/common/ssh_commands.py
aurora_cli/src/base/common/groups/device/__init__.py
aurora_cli/src/base/common/groups/device/device_features.py
aurora_cli/src/base/common/groups/device/device_package_features.py
aurora_cli/src/base/common/groups/emulator/__init__.py
aurora_cli/src/base/common/groups/emulator/__tools.py
aurora_cli/src/base/common/groups/emulator/emulator_features.py
aurora_cli-3.2.11.dist-info/LICENSE
aurora_cli-3.2.11.dist-info/METADATA
aurora_cli-3.2.11.dist-info/WHEEL
aurora_cli-3.2.11.dist-info/entry_points.txt
aurora_cli-3.2.11.dist-info/top_level.txt
aurora_cli-3.2.11.dist-info/RECORD
