Metadata-Version: 2.2
Name: aurora-cli
Version: 3.2.11
Summary: An application that simplifies the life of an application developer for the Aurora OS.
Home-page: https://github.com/keygenqt/aurora-cli
Author: Vitaliy Zarubin
Author-email: keygenqt@gmail.com
Requires-Python: >=3.8.10
License-File: LICENSE
Requires-Dist: click>=8.1.7
Requires-Dist: requests>=2.31.0
Requires-Dist: alive-progress>=3.2.0
Requires-Dist: pyYaml>=6.0.1
Requires-Dist: paramiko>=3.4.0
Requires-Dist: cffi>=1.16.0
Requires-Dist: GitPython>=3.1.41
Requires-Dist: beautifulsoup4>=4.12.3
Requires-Dist: weasyprint>=61.1
Requires-Dist: pillow>=10.2.0
Requires-Dist: diskcache>=5.6.3
Requires-Dist: rpmfile>=2.1.0
Requires-Dist: packaging>=24.1
Dynamic: author
Dynamic: author-email
Dynamic: description
Dynamic: description-content-type
Dynamic: home-page
Dynamic: requires-dist
Dynamic: requires-python
Dynamic: summary
